LICENSE
MANIFEST.in
README.md
setup.cfg
setup.py
lobster/__init__.py
lobster/__main__.py
lobster/audio.py
lobster/downloader.py
lobster/exceptions.py
lobster/filemanager.py
lobster/parser.py
lobster/prompt.py
lobster/prompt_messages.py
lobster/validator.py
lobster.egg-info/PKG-INFO
lobster.egg-info/SOURCES.txt
lobster.egg-info/dependency_links.txt
lobster.egg-info/entry_points.txt
lobster.egg-info/requires.txt
lobster.egg-info/top_level.txt