Metadata-Version: 1.1
Name: lobster
Version: 0.3.1
Summary: Split audio files into tracks with a single command
Home-page: https://github.com/noahfx/lobster
Author: Josue Ortega
Author-email: josueortega@protonmail.ch
License: MIT
Keywords: audio track edit cut youtube ffmpeg mp3 ogg split music download
Platform: UNKNOWN
Classifier: Development Status :: 3 - Alpha
Classifier: License :: OSI Approved :: MIT License
Classifier: Operating System :: OS Independent
Classifier: Programming Language :: Python
Classifier: Programming Language :: Python :: 3
Classifier: Topic :: Multimedia :: Sound/Audio
